tokra_shield/__init__.py
tokra_shield/__main__.py
tokra_shield/api.py
tokra_shield/branding.py
tokra_shield/cli.py
tokra_shield/config.py
tokra_shield/detector.py
tokra_shield/engine.py
tokra_shield/filters.py
tokra_shield/ghost_loader.py
tokra_shield/normalizer.py
tokra_shield/ghost/__init__.py
tokra_shield/ghost/ar.json
tokra_shield/ghost/en.json
tokra_shield-0.1.0.dist-info/licenses/LICENSE
tokra_shield-0.1.0.dist-info/licenses/NOTICE
tokra_shield-0.1.0.dist-info/METADATA
tokra_shield-0.1.0.dist-info/WHEEL
tokra_shield-0.1.0.dist-info/entry_points.txt
tokra_shield-0.1.0.dist-info/top_level.txt
tokra_shield-0.1.0.dist-info/RECORD
