Metadata-Version: 2.4
Name: tokra-shield
Version: 0.1.0
Summary: Lightweight, dependency‑free content‑protection SDK
Author: Tokra Community
License-Expression: Apache-2.0
Keywords: content-safety,spam,scam,prompt-injection
Requires-Python: >=3.8
License-File: LICENSE
License-File: NOTICE
Dynamic: license-file
